Metadata-Version: 1.1
Name: fnx-wac
Version: 0.33
Summary: Writing RESTful API clients.
Home-page: https://github.com/finix-payments/fnx-wac
Author: Finix
Author-email: dev@finixpayments.com
License: Copyright (c) 2014 Balanced.
